MySBdt/MySBdt.py
MySBdt/__init__.py
mysoftbank/__init__.py
mysoftbank/mysoftbank.py
mysb_scraping-5.0.dist-info/METADATA
mysb_scraping-5.0.dist-info/WHEEL
mysb_scraping-5.0.dist-info/top_level.txt
mysb_scraping-5.0.dist-info/RECORD
