Metadata-Version: 2.1
Name: mysb-scraping
Version: 5.0
Summary: Remaining data notifications with LINE Notify
Home-page: https://github.com/miya/mysb-scraping
Author: miya
Author-email: m0zurillex@gmail.com
License: UNKNOWN
Keywords: softbank,scraping
Platform: UNKNOWN
Requires-Dist: lxml
Requires-Dist: requests
Requires-Dist: beautifulsoup4
